Workbook

Sheet Inputs
A1: 2026 Tax Outline — Inputs
A2: Alberta resident · employee salary + self-employed trading (business income)
A3: Edit the yellow cells:
A4: Hourly wage ($/hr) | B4: 22 | C4: Your full-time job wage. Value provided by you.
A5: Hours per week | B5: 40 | C5: Assumed full-time. Edit if different.
A6: Weeks paid per year | B6: 52 | C6: Assumed paid 52 weeks. Edit if different.
A7: Monthly rent ($) | B7: 1375 | C7: Value provided by you. Used only for the home-office deduction.
A8: Home office share of rent | B8: 0.15 | C8: Assumption: 15% of the home used principally for trading. Set to your actual workspace %; CRA expects a reasonable, documented figure.
A9: Other annual trading expenses ($) | B9: 0 | C9: Data feeds, platform fees, hardware, etc. Deductible against trading profit.
A11: Legend
A12: Blue text on yellow | C12: Input — edit these (here and the trading-profit row on 'Tax Calc').
A13: Black text | C13: Formula — leave alone; recalculates from inputs.
A14: Green text | C14: Value pulled from another sheet.
A16: Example: at $22/hr, 40 hrs, 52 weeks, the salary computes to $45,760 on the Tax Calc sheet.

Sheet Tax Data 2026
A1: 2026 Tax Parameters (Canada + Alberta)
A2: Source: data/json/*.json in this repository (CRA/provincial figures, collected 2026-08-18 — see README.md for provenance).
A4: Federal brackets
A5: From | B5: To | C5: Rate
A6: 0 | B6: 58523 | C6: 0.14
A7: 58523 | B7: 117045 | C7: 0.205
A8: 117045 | B8: 181440 | C8: 0.26
A9: 181440 | B9: 258482 | C9: 0.29
A10: 258482 | B10: 1000000000 | C10: 0.33
A12: Alberta brackets
A13: From | B13: To | C13: Rate
A14: 0 | B14: 61200 | C14: 0.08
A15: 61200 | B15: 151234 | C15: 0.1
A16: 151234 | B16: 181480 | C16: 0.12
A17: 181480 | B17: 241975 | C17: 0.13
A18: 241975 | B18: 362962 | C18: 0.14
A19: 362962 | B19: 1000000000 | C19: 0.15
A21: Other parameters
A22: Federal basic personal amount | B22: 16452 | E22: Maximum BPA; the phase-out starts at $181,440 net income — far above this model's incomes, so not modelled.
A23: Alberta basic personal amount | B23: 22769
A24: Canada employment amount | B24: 1500 | E24: Estimate: 2025 amount $1,471 x 1.02 federal indexation, rounded. Federal credit base for employees.
A25: CPP YMPE | B25: 74600
A26: CPP basic exemption | B26: 3500
A27: CPP employee rate | B27: 0.0595
A28: CPP self-employed rate | B28: 0.119
A29: CPP2 YAMPE | B29: 85000
A30: CPP2 self-employed rate | B30: 0.08
A31: EI max insurable earnings | B31: 68900
A32: EI employee rate | B32: 0.0163 | E32: No EI is payable (or claimable) on self-employment income unless you opt in.

Sheet Tax Calc
A1: 2026 Tax Calculation — Salary + Scalp Trading (Alberta)
A2: Column B is your salary with no trading (reference). C is your situation; D and E are what-if profit levels — all three yellow cells are editable.
B4: Salary only | C4: Your case | D4: What-if | E4: What-if
A6: INCOME
A7: Trading profit (gross) | B7: 0 | C7: 10000 | D7: 25000 | E7: 50000
A8: Home office deduction | B8: =-MIN(Inputs!$B$7*12*Inputs!$B$8,B7) | C8: =-MIN(Inputs!$B$7*12*Inputs!$B$8,C7) | D8: =-MIN(Inputs!$B$7*12*Inputs!$B$8,D7) | E8: =-MIN(Inputs!$B$7*12*Inputs!$B$8,E7)
A9: Other trading expenses | B9: =-MIN(Inputs!$B$9,B7+B8) | C9: =-MIN(Inputs!$B$9,C7+C8) | D9: =-MIN(Inputs!$B$9,D7+D8) | E9: =-MIN(Inputs!$B$9,E7+E8)
A10: Net trading income | B10: =B7+B8+B9 | C10: =C7+C8+C9 | D10: =D7+D8+D9 | E10: =E7+E8+E9
A11: Employment income | B11: =Inputs!$B$4*Inputs!$B$5*Inputs!$B$6 | C11: =$B$11 | D11: =$B$11 | E11: =$B$11
A12: Total income | B12: =B10+B11 | C12: =C10+C11 | D12: =D10+D11 | E12: =E10+E11
A14: PAYROLL CONTRIBUTIONS
A15: Employee CPP (withheld from pay) | B15: =(MIN(B11,'Tax Data 2026'!$B$25)-'Tax Data 2026'!$B$26)*'Tax Data 2026'!$B$27 | C15: =(MIN(C11,'Tax Data 2026'!$B$25)-'Tax Data 2026'!$B$26)*'Tax Data 2026'!$B$27 | D15: =(MIN(D11,'Tax Data 2026'!$B$25)-'Tax Data 2026'!$B$26)*'Tax Data 2026'!$B$27 | E15: =(MIN(E11,'Tax Data 2026'!$B$25)-'Tax Data 2026'!$B$26)*'Tax Data 2026'!$B$27
A16: EI premiums (withheld from pay) | B16: =MIN(B11,'Tax Data 2026'!$B$31)*'Tax Data 2026'!$B$32 | C16: =MIN(C11,'Tax Data 2026'!$B$31)*'Tax Data 2026'!$B$32 | D16: =MIN(D11,'Tax Data 2026'!$B$31)*'Tax Data 2026'!$B$32 | E16: =MIN(E11,'Tax Data 2026'!$B$31)*'Tax Data 2026'!$B$32
A17: Self-employed CPP on trading | B17: =(MIN(B11+B10,'Tax Data 2026'!$B$25)-MIN(B11,'Tax Data 2026'!$B$25))*'Tax Data 2026'!$B$28 | C17: =(MIN(C11+C10,'Tax Data 2026'!$B$25)-MIN(C11,'Tax Data 2026'!$B$25))*'Tax Data 2026'!$B$28 | D17: =(MIN(D11+D10,'Tax Data 2026'!$B$25)-MIN(D11,'Tax Data 2026'!$B$25))*'Tax Data 2026'!$B$28 | E17: =(MIN(E11+E10,'Tax Data 2026'!$B$25)-MIN(E11,'Tax Data 2026'!$B$25))*'Tax Data 2026'!$B$28
A18: Self-employed CPP2 on trading | B18: =MAX(0,MIN(B11+B10,'Tax Data 2026'!$B$29)-MAX(B11,'Tax Data 2026'!$B$25))*'Tax Data 2026'!$B$30 | C18: =MAX(0,MIN(C11+C10,'Tax Data 2026'!$B$29)-MAX(C11,'Tax Data 2026'!$B$25))*'Tax Data 2026'!$B$30 | D18: =MAX(0,MIN(D11+D10,'Tax Data 2026'!$B$29)-MAX(D11,'Tax Data 2026'!$B$25))*'Tax Data 2026'!$B$30 | E18: =MAX(0,MIN(E11+E10,'Tax Data 2026'!$B$29)-MAX(E11,'Tax Data 2026'!$B$25))*'Tax Data 2026'!$B$30
A20: TAXABLE INCOME
A21: Deduction: half of self-employed CPP | B21: =-0.5*(B17+B18) | C21: =-0.5*(C17+C18) | D21: =-0.5*(D17+D18) | E21: =-0.5*(E17+E18)
A22: Taxable income | B22: =B12+B21 | C22: =C12+C21 | D22: =D12+D21 | E22: =E12+E21
A24: FEDERAL TAX
A25: Bracket 1 | B25: =MAX(0,MIN(B$22,'Tax Data 2026'!$B$6)-'Tax Data 2026'!$A$6)*'Tax Data 2026'!$C$6 | C25: =MAX(0,MIN(C$22,'Tax Data 2026'!$B$6)-'Tax Data 2026'!$A$6)*'Tax Data 2026'!$C$6 | D25: =MAX(0,MIN(D$22,'Tax Data 2026'!$B$6)-'Tax Data 2026'!$A$6)*'Tax Data 2026'!$C$6 | E25: =MAX(0,MIN(E$22,'Tax Data 2026'!$B$6)-'Tax Data 2026'!$A$6)*'Tax Data 2026'!$C$6
A26: Bracket 2 | B26: =MAX(0,MIN(B$22,'Tax Data 2026'!$B$7)-'Tax Data 2026'!$A$7)*'Tax Data 2026'!$C$7 | C26: =MAX(0,MIN(C$22,'Tax Data 2026'!$B$7)-'Tax Data 2026'!$A$7)*'Tax Data 2026'!$C$7 | D26: =MAX(0,MIN(D$22,'Tax Data 2026'!$B$7)-'Tax Data 2026'!$A$7)*'Tax Data 2026'!$C$7 | E26: =MAX(0,MIN(E$22,'Tax Data 2026'!$B$7)-'Tax Data 2026'!$A$7)*'Tax Data 2026'!$C$7
A27: Bracket 3 | B27: =MAX(0,MIN(B$22,'Tax Data 2026'!$B$8)-'Tax Data 2026'!$A$8)*'Tax Data 2026'!$C$8 | C27: =MAX(0,MIN(C$22,'Tax Data 2026'!$B$8)-'Tax Data 2026'!$A$8)*'Tax Data 2026'!$C$8 | D27: =MAX(0,MIN(D$22,'Tax Data 2026'!$B$8)-'Tax Data 2026'!$A$8)*'Tax Data 2026'!$C$8 | E27: =MAX(0,MIN(E$22,'Tax Data 2026'!$B$8)-'Tax Data 2026'!$A$8)*'Tax Data 2026'!$C$8
A28: Bracket 4 | B28: =MAX(0,MIN(B$22,'Tax Data 2026'!$B$9)-'Tax Data 2026'!$A$9)*'Tax Data 2026'!$C$9 | C28: =MAX(0,MIN(C$22,'Tax Data 2026'!$B$9)-'Tax Data 2026'!$A$9)*'Tax Data 2026'!$C$9 | D28: =MAX(0,MIN(D$22,'Tax Data 2026'!$B$9)-'Tax Data 2026'!$A$9)*'Tax Data 2026'!$C$9 | E28: =MAX(0,MIN(E$22,'Tax Data 2026'!$B$9)-'Tax Data 2026'!$A$9)*'Tax Data 2026'!$C$9
A29: Bracket 5 | B29: =MAX(0,MIN(B$22,'Tax Data 2026'!$B$10)-'Tax Data 2026'!$A$10)*'Tax Data 2026'!$C$10 | C29: =MAX(0,MIN(C$22,'Tax Data 2026'!$B$10)-'Tax Data 2026'!$A$10)*'Tax Data 2026'!$C$10 | D29: =MAX(0,MIN(D$22,'Tax Data 2026'!$B$10)-'Tax Data 2026'!$A$10)*'Tax Data 2026'!$C$10 | E29: =MAX(0,MIN(E$22,'Tax Data 2026'!$B$10)-'Tax Data 2026'!$A$10)*'Tax Data 2026'!$C$10
A30: Federal tax before credits | B30: =SUM(B25:B29) | C30: =SUM(C25:C29) | D30: =SUM(D25:D29) | E30: =SUM(E25:E29)
A31: Non-refundable credits (14%) | B31: =-0.14*('Tax Data 2026'!$B$22+'Tax Data 2026'!$B$24+B15+B16+0.5*B17) | C31: =-0.14*('Tax Data 2026'!$B$22+'Tax Data 2026'!$B$24+C15+C16+0.5*C17) | D31: =-0.14*('Tax Data 2026'!$B$22+'Tax Data 2026'!$B$24+D15+D16+0.5*D17) | E31: =-0.14*('Tax Data 2026'!$B$22+'Tax Data 2026'!$B$24+E15+E16+0.5*E17)
A32: Federal tax payable | B32: =MAX(0,B30+B31) | C32: =MAX(0,C30+C31) | D32: =MAX(0,D30+D31) | E32: =MAX(0,E30+E31)
A34: ALBERTA TAX
A35: Bracket 1 | B35: =MAX(0,MIN(B$22,'Tax Data 2026'!$B$14)-'Tax Data 2026'!$A$14)*'Tax Data 2026'!$C$14 | C35: =MAX(0,MIN(C$22,'Tax Data 2026'!$B$14)-'Tax Data 2026'!$A$14)*'Tax Data 2026'!$C$14 | D35: =MAX(0,MIN(D$22,'Tax Data 2026'!$B$14)-'Tax Data 2026'!$A$14)*'Tax Data 2026'!$C$14 | E35: =MAX(0,MIN(E$22,'Tax Data 2026'!$B$14)-'Tax Data 2026'!$A$14)*'Tax Data 2026'!$C$14
A36: Bracket 2 | B36: =MAX(0,MIN(B$22,'Tax Data 2026'!$B$15)-'Tax Data 2026'!$A$15)*'Tax Data 2026'!$C$15 | C36: =MAX(0,MIN(C$22,'Tax Data 2026'!$B$15)-'Tax Data 2026'!$A$15)*'Tax Data 2026'!$C$15 | D36: =MAX(0,MIN(D$22,'Tax Data 2026'!$B$15)-'Tax Data 2026'!$A$15)*'Tax Data 2026'!$C$15 | E36: =MAX(0,MIN(E$22,'Tax Data 2026'!$B$15)-'Tax Data 2026'!$A$15)*'Tax Data 2026'!$C$15
A37: Bracket 3 | B37: =MAX(0,MIN(B$22,'Tax Data 2026'!$B$16)-'Tax Data 2026'!$A$16)*'Tax Data 2026'!$C$16 | C37: =MAX(0,MIN(C$22,'Tax Data 2026'!$B$16)-'Tax Data 2026'!$A$16)*'Tax Data 2026'!$C$16 | D37: =MAX(0,MIN(D$22,'Tax Data 2026'!$B$16)-'Tax Data 2026'!$A$16)*'Tax Data 2026'!$C$16 | E37: =MAX(0,MIN(E$22,'Tax Data 2026'!$B$16)-'Tax Data 2026'!$A$16)*'Tax Data 2026'!$C$16
A38: Bracket 4 | B38: =MAX(0,MIN(B$22,'Tax Data 2026'!$B$17)-'Tax Data 2026'!$A$17)*'Tax Data 2026'!$C$17 | C38: =MAX(0,MIN(C$22,'Tax Data 2026'!$B$17)-'Tax Data 2026'!$A$17)*'Tax Data 2026'!$C$17 | D38: =MAX(0,MIN(D$22,'Tax Data 2026'!$B$17)-'Tax Data 2026'!$A$17)*'Tax Data 2026'!$C$17 | E38: =MAX(0,MIN(E$22,'Tax Data 2026'!$B$17)-'Tax Data 2026'!$A$17)*'Tax Data 2026'!$C$17
A39: Bracket 5 | B39: =MAX(0,MIN(B$22,'Tax Data 2026'!$B$18)-'Tax Data 2026'!$A$18)*'Tax Data 2026'!$C$18 | C39: =MAX(0,MIN(C$22,'Tax Data 2026'!$B$18)-'Tax Data 2026'!$A$18)*'Tax Data 2026'!$C$18 | D39: =MAX(0,MIN(D$22,'Tax Data 2026'!$B$18)-'Tax Data 2026'!$A$18)*'Tax Data 2026'!$C$18 | E39: =MAX(0,MIN(E$22,'Tax Data 2026'!$B$18)-'Tax Data 2026'!$A$18)*'Tax Data 2026'!$C$18
A40: Bracket 6 | B40: =MAX(0,MIN(B$22,'Tax Data 2026'!$B$19)-'Tax Data 2026'!$A$19)*'Tax Data 2026'!$C$19 | C40: =MAX(0,MIN(C$22,'Tax Data 2026'!$B$19)-'Tax Data 2026'!$A$19)*'Tax Data 2026'!$C$19 | D40: =MAX(0,MIN(D$22,'Tax Data 2026'!$B$19)-'Tax Data 2026'!$A$19)*'Tax Data 2026'!$C$19 | E40: =MAX(0,MIN(E$22,'Tax Data 2026'!$B$19)-'Tax Data 2026'!$A$19)*'Tax Data 2026'!$C$19
A41: Alberta tax before credits | B41: =SUM(B35:B40) | C41: =SUM(C35:C40) | D41: =SUM(D35:D40) | E41: =SUM(E35:E40)
A42: Non-refundable credits (8%) | B42: =-0.08*('Tax Data 2026'!$B$23+B15+B16+0.5*B17) | C42: =-0.08*('Tax Data 2026'!$B$23+C15+C16+0.5*C17) | D42: =-0.08*('Tax Data 2026'!$B$23+D15+D16+0.5*D17) | E42: =-0.08*('Tax Data 2026'!$B$23+E15+E16+0.5*E17)
A43: Alberta tax payable | B43: =MAX(0,B41+B42) | C43: =MAX(0,C41+C42) | D43: =MAX(0,D41+D42) | E43: =MAX(0,E41+E42)
A45: RESULTS
A46: Total income tax | B46: =B32+B43 | C46: =C32+C43 | D46: =D32+D43 | E46: =E32+E43
A47: Total tax + all CPP/EI | B47: =B46+B15+B16+B17+B18 | C47: =C46+C15+C16+C17+C18 | D47: =D46+D15+D16+D17+D18 | E47: =E46+E15+E16+E17+E18
A48: After-tax income | B48: =B12-B47 | C48: =C12-C47 | D48: =D12-D47 | E48: =E12-E47
A49: Average rate (on total income) | B49: =IF(B12=0,0,B47/B12) | C49: =IF(C12=0,0,C47/C12) | D49: =IF(D12=0,0,D47/D12) | E49: =IF(E12=0,0,E47/E12)
A51: Cost of trading vs salary-only | C51: =C47-$B$47 | D51: =D47-$B$47 | E51: =E47-$B$47
A52: Effective rate on trading profit | C52: =IF(C7=0,0,C51/C7) | D52: =IF(D7=0,0,D51/D7) | E52: =IF(E7=0,0,E51/E7)
A53: Set aside per $100 of trading profit | C53: =C52*100 | D53: =D52*100 | E53: =E52*100
A55: Notes: 2026 rules, Alberta resident, single filer, no other income/deductions. Employer withholding assumed to cover the salary-only liability. No EI on self-employment income (opt-in not assumed). Estimates for planning, not filing — see docs/trader_taxation.md.

Sheet All Income Brackets
A1: Personal Income Tax Brackets 2026 — All of Canada
A2: Federal + every province/territory. Source: data/json/personal_income_tax_2026.json (CRA figures; see README.md).
A4: Jurisdiction | B4: Bracket | C4: From | D4: To | E4: Marginal rate
A5: Canada (federal) | B5: 1 | C5: 0 | D5: 58523 | E5: 0.14
A6: Canada (federal) | B6: 2 | C6: 58523 | D6: 117045 | E6: 0.205
A7: Canada (federal) | B7: 3 | C7: 117045 | D7: 181440 | E7: 0.26
A8: Canada (federal) | B8: 4 | C8: 181440 | D8: 258482 | E8: 0.29
A9: Canada (federal) | B9: 5 | C9: 258482 | D9: no limit | E9: 0.33
A10: Alberta | B10: 1 | C10: 0 | D10: 61200 | E10: 0.08
A11: Alberta | B11: 2 | C11: 61200 | D11: 151234 | E11: 0.1
A12: Alberta | B12: 3 | C12: 151234 | D12: 181480 | E12: 0.12
A13: Alberta | B13: 4 | C13: 181480 | D13: 241975 | E13: 0.13
A14: Alberta | B14: 5 | C14: 241975 | D14: 362962 | E14: 0.14
A15: Alberta | B15: 6 | C15: 362962 | D15: no limit | E15: 0.15
A16: British Columbia | B16: 1 | C16: 0 | D16: 50363 | E16: 0.056
A17: British Columbia | B17: 2 | C17: 50363 | D17: 100728 | E17: 0.077
A18: British Columbia | B18: 3 | C18: 100728 | D18: 115647 | E18: 0.105
A19: British Columbia | B19: 4 | C19: 115647 | D19: 140430 | E19: 0.1229
A20: British Columbia | B20: 5 | C20: 140430 | D20: 190405 | E20: 0.147
A21: British Columbia | B21: 6 | C21: 190405 | D21: 265545 | E21: 0.168
A22: British Columbia | B22: 7 | C22: 265545 | D22: no limit | E22: 0.205
A23: Saskatchewan | B23: 1 | C23: 0 | D23: 54532 | E23: 0.105
A24: Saskatchewan | B24: 2 | C24: 54532 | D24: 155805 | E24: 0.125
A25: Saskatchewan | B25: 3 | C25: 155805 | D25: no limit | E25: 0.145
A26: Manitoba | B26: 1 | C26: 0 | D26: 47564 | E26: 0.108
A27: Manitoba | B27: 2 | C27: 47564 | D27: 101200 | E27: 0.1275
A28: Manitoba | B28: 3 | C28: 101200 | D28: no limit | E28: 0.174
A29: Ontario | B29: 1 | C29: 0 | D29: 53891 | E29: 0.0505
A30: Ontario | B30: 2 | C30: 53891 | D30: 107785 | E30: 0.0915
A31: Ontario | B31: 3 | C31: 107785 | D31: 150000 | E31: 0.1116
A32: Ontario | B32: 4 | C32: 150000 | D32: 220000 | E32: 0.1216
A33: Ontario | B33: 5 | C33: 220000 | D33: no limit | E33: 0.1316
A34: Quebec | B34: 1 | C34: 0 | D34: 54345 | E34: 0.14
A35: Quebec | B35: 2 | C35: 54345 | D35: 108680 | E35: 0.19
A36: Quebec | B36: 3 | C36: 108680 | D36: 132245 | E36: 0.24
A37: Quebec | B37: 4 | C37: 132245 | D37: no limit | E37: 0.2575
A38: New Brunswick | B38: 1 | C38: 0 | D38: 52332 | E38: 0.094
A39: New Brunswick | B39: 2 | C39: 52332 | D39: 104666 | E39: 0.14
A40: New Brunswick | B40: 3 | C40: 104666 | D40: 193861 | E40: 0.16
A41: New Brunswick | B41: 4 | C41: 193861 | D41: no limit | E41: 0.195
A42: Nova Scotia | B42: 1 | C42: 0 | D42: 30995 | E42: 0.0879
A43: Nova Scotia | B43: 2 | C43: 30995 | D43: 61991 | E43: 0.1495
A44: Nova Scotia | B44: 3 | C44: 61991 | D44: 97417 | E44: 0.1667
A45: Nova Scotia | B45: 4 | C45: 97417 | D45: 157124 | E45: 0.175
A46: Nova Scotia | B46: 5 | C46: 157124 | D46: no limit | E46: 0.21
A47: Prince Edward Island | B47: 1 | C47: 0 | D47: 33928 | E47: 0.095
A48: Prince Edward Island | B48: 2 | C48: 33928 | D48: 65820 | E48: 0.1347
A49: Prince Edward Island | B49: 3 | C49: 65820 | D49: 106890 | E49: 0.166
A50: Prince Edward Island | B50: 4 | C50: 106890 | D50: 142520 | E50: 0.1762
A51: Prince Edward Island | B51: 5 | C51: 142520 | D51: no limit | E51: 0.19
A52: Newfoundland and Labrador | B52: 1 | C52: 0 | D52: 44678 | E52: 0.087
A53: Newfoundland and Labrador | B53: 2 | C53: 44678 | D53: 89354 | E53: 0.145
A54: Newfoundland and Labrador | B54: 3 | C54: 89354 | D54: 159528 | E54: 0.158
A55: Newfoundland and Labrador | B55: 4 | C55: 159528 | D55: 223340 | E55: 0.178
A56: Newfoundland and Labrador | B56: 5 | C56: 223340 | D56: 285319 | E56: 0.198
A57: Newfoundland and Labrador | B57: 6 | C57: 285319 | D57: 570638 | E57: 0.208
A58: Newfoundland and Labrador | B58: 7 | C58: 570638 | D58: 1141275 | E58: 0.213
A59: Newfoundland and Labrador | B59: 8 | C59: 1141275 | D59: no limit | E59: 0.218
A60: Yukon | B60: 1 | C60: 0 | D60: 58523 | E60: 0.064
A61: Yukon | B61: 2 | C61: 58523 | D61: 117045 | E61: 0.09
A62: Yukon | B62: 3 | C62: 117045 | D62: 181440 | E62: 0.109
A63: Yukon | B63: 4 | C63: 181440 | D63: 500000 | E63: 0.128
A64: Yukon | B64: 5 | C64: 500000 | D64: no limit | E64: 0.15
A65: Northwest Territories | B65: 1 | C65: 0 | D65: 53003 | E65: 0.059
A66: Northwest Territories | B66: 2 | C66: 53003 | D66: 106009 | E66: 0.086
A67: Northwest Territories | B67: 3 | C67: 106009 | D67: 172346 | E67: 0.122
A68: Northwest Territories | B68: 4 | C68: 172346 | D68: no limit | E68: 0.1405
A69: Nunavut | B69: 1 | C69: 0 | D69: 55801 | E69: 0.04
A70: Nunavut | B70: 2 | C70: 55801 | D70: 111601 | E70: 0.07
A71: Nunavut | B71: 3 | C71: 111601 | D71: 181439 | E71: 0.09
A72: Nunavut | B72: 4 | C72: 181439 | D72: no limit | E72: 0.115
A74: Basic personal amounts
A75: Jurisdiction | B75: BPA
A76: Canada (federal) | B76: 16452 | C76: Phases down to $14,829 between $181,440 and $258,482 of net income
A77: Alberta | B77: 22769
A78: British Columbia | B78: 13217
A79: Saskatchewan | B79: 19371
A80: Manitoba | B80: 15780
A81: Ontario | B81: 12989
A82: Quebec | B82: 18952
A83: New Brunswick | B83: 13664
A84: Nova Scotia | B84: 11932
A85: Prince Edward Island | B85: n/a
A86: Newfoundland and Labrador | B86: 11189
A87: Yukon | B87: 16452 | C87: Phases down to $14,829 between $181,440 and $258,482 of net income
A88: Northwest Territories | B88: 18199
A89: Nunavut | B89: 19659

Sheet Sales Tax
A1: Sales Tax Rates 2026 — GST / HST / PST / QST
A2: Source: data/json/sales_tax_2026.json.
A4: Province/Territory | B4: System | C4: GST | D4: PST/QST | E4: HST | F4: Total
A5: Alberta | B5: GST | C5: 0.05 | D5: 0 | E5: - | F5: 0.05
A6: British Columbia | B6: GST + PST | C6: 0.05 | D6: 0.07 | E6: - | F6: 0.12
A7: Saskatchewan | B7: GST + PST | C7: 0.05 | D7: 0.06 | E7: - | F7: 0.11
A8: Manitoba | B8: GST + RST | C8: 0.05 | D8: 0.07 | E8: - | F8: 0.12
A9: Ontario | B9: HST | C9: - | D9: - | E9: 0.13 | F9: 0.13
A10: Quebec | B10: GST + QST | C10: 0.05 | D10: 0.09975 | E10: - | F10: 0.14975
A11: New Brunswick | B11: HST | C11: - | D11: - | E11: 0.15 | F11: 0.15
A12: Nova Scotia | B12: HST | C12: - | D12: - | E12: 0.14 | F12: 0.14 | G12: HST reduced from 15% to 14% effective April 1, 2025.
A13: Prince Edward Island | B13: HST | C13: - | D13: - | E13: 0.15 | F13: 0.15
A14: Newfoundland and Labrador | B14: HST | C14: - | D14: - | E14: 0.15 | F14: 0.15
A15: Yukon | B15: GST | C15: 0.05 | D15: 0 | E15: - | F15: 0.05
A16: Northwest Territories | B16: GST | C16: 0.05 | D16: 0 | E16: - | F16: 0.05
A17: Nunavut | B17: GST | C17: 0.05 | D17: 0 | E17: - | F17: 0.05

Sheet Payroll CPP EI
A1: Payroll Contributions 2026 — CPP, CPP2, QPP, EI, QPIP
A2: Source: data/json/payroll_contributions_2026.json.
A4: Canada Pension Plan (base + first additional)
A5: ympe | B5: 74600
A6: basic exemption | B6: 3500
A7: employee rate | B7: 0.0595
A8: employer rate | B8: 0.0595
A9: self employed rate | B9: 0.119
A10: max employee contribution | B10: 4230.45
A11: max self employed contribution | B11: 8460.9
A12: YMPE (Year's Maximum Pensionable Earnings) rose from $71,300 in 2025 to $74,600 in 2026.
A14: CPP second additional contribution (CPP2)
A15: yampe | B15: 85000
A16: employee rate | B16: 0.04
A17: employer rate | B17: 0.04
A18: self employed rate | B18: 0.08
A19: max employee contribution | B19: 416
A20: max self employed contribution | B20: 832
A21: Applies to pensionable earnings between the YMPE and the YAMPE (Year's Additional Maximum Pensionable Earnings, $85,000 in 2026, up from $81,200 in 2025).
A23: Quebec Pension Plan (base + first additional)
A24: ympe | B24: 74600
A25: basic exemption | B25: 3500
A26: employee rate | B26: 0.063
A27: employer rate | B27: 0.063
A28: self employed rate | B28: 0.126
A29: max employee contribution | B29: 4479.3
A30: max self employed contribution | B30: 8958.6
A31: Quebec reduced the QPP first-tier rate to 6.30% for 2026 (it was 6.40% in 2025). Self-employed Quebec workers pay both halves (12.60%). QPP2 is a separate object in this file, mirroring the cpp2 shape.
A33: QPP second additional contribution (QPP2)
A34: yampe | B34: 85000
A35: employee rate | B35: 0.04
A36: employer rate | B36: 0.04
A37: self employed rate | B37: 0.08
A38: max employee contribution | B38: 416
A39: max self employed contribution | B39: 832
A40: QPP2 mirrors CPP2: 4% employee (8% self-employed) on pensionable earnings between the YMPE and the YAMPE.
A42: Employment Insurance
A43: maximum insurable earnings | B43: 68900
A44: employee rate | B44: 0.0163
A45: employer rate multiplier | B45: 1.4
A46: employer rate | B46: 0.02282
A47: max employee premium | B47: 1123.07
A48: max employer premium per employee | B48: 1572.3
A49: Quebec employee rate | B49: 0.013
A50: Quebec employer rate | B50: 0.0182
A51: Quebec max employee premium | B51: 895.7
A52: Maximum insurable earnings rose from $65,700 in 2025 to $68,900 in 2026; the employee rate is $1.63 per $100 of insurable earnings.
A54: Quebec Parental Insurance Plan
A55: maximum insurable earnings | B55: 103000
A56: employee rate | B56: 0.0043
A57: employer rate | B57: 0.00602
A58: max employee premium | B58: 442.9
A59: max employer premium per employee | B59: 620.06
A60: QPIP premium rates fell for 2026 (employee rate from 0.494% to 0.430%) while the insurable earnings maximum rose to $103,000.

Sheet Corporate Tax
A1: Corporate Income Tax Rates 2026
A2: Source: data/json/corporate_income_tax_2026.json.
A4: Jurisdiction | B4: General rate | C4: Small business rate | D4: SB limit | E4: Notes
A5: Canada (federal) | B5: 0.15 | C5: 0.09 | D5: 500000
A6: Alberta | B6: 0.08 | C6: 0.02 | D6: 500000
A7: British Columbia | B7: 0.12 | C7: 0.02 | D7: 500000
A8: Saskatchewan | B8: 0.12 | C8: 0.01 | D8: 600000 | E8: Saskatchewan's 1% small-business rate was made permanent in 2025; its business limit is $600,000, the only province above $500,000.
A9: Manitoba | B9: 0.12 | C9: 0 | D9: 500000
A10: Ontario | B10: 0.115 | C10: 0.032 | D10: 500000 | E10: Small-business rate reduced from 3.2% to 2.2% for taxation years beginning on or after July 1, 2026.
A11: Quebec | B11: 0.115 | C11: 0.032 | D11: 500000 | E11: Small-business rate reduced from 3.2% to 2.2% for taxation years beginning after April 29, 2026. Quebec's small-business rate requires minimum employee paid-hours; corporations that do not qualify pay the general rate.
A12: New Brunswick | B12: 0.14 | C12: 0.025 | D12: 500000
A13: Nova Scotia | B13: 0.14 | C13: 0.015 | D13: 500000 | E13: General rate cut from 16% to 14% and small-business rate from 2.5% to 1.5% effective April 1, 2025.
A14: Prince Edward Island | B14: 0.16 | C14: 0.01 | D14: 500000
A15: Newfoundland and Labrador | B15: 0.15 | C15: 0.02 | D15: 500000 | E15: Small-business rate reduced from 2.5% to 2.0% effective January 1, 2026.
A16: Yukon | B16: 0.12 | C16: 0 | D16: 500000
A17: Northwest Territories | B17: 0.115 | C17: 0.02 | D17: 500000
A18: Nunavut | B18: 0.12 | C18: 0.03 | D18: 500000

Sheet Credits & Limits
A1: Key Credits, Registered Accounts & System Parameters 2026
A2: Source: data/json/credits_and_limits_2026.json.
A4: TFSA annual limit | B4: 7000 | C4: Cumulative room applies to someone 18+ in 2009 who has never contributed.
A5: TFSA cumulative room since 2009 | B5: 109000
A6: RRSP annual limit | B6: 33810 | C6: 18% of previous year's earned income, up to the annual limit; unused room carries forward indefinitely.
A7: FHSA annual limit | B7: 8000 | C7: Maximum single-year contribution is $16,000 ($8,000 annual + $8,000 carried forward).
A8: FHSA lifetime limit | B8: 40000
A9: Federal BPA (max) | B9: 16452
A10: Federal BPA (min, high income) | B10: 14829
A11: Federal credit rate | B11: 0.14 | C11: Federal non-refundable credits are valued at the lowest federal rate (14% in 2026). Provincial credits use each province's lowest rate.
A12: OAS clawback threshold | B12: 95323 | C12: OAS recovery tax: 15% of net income above the threshold for the 2026 income year.
A13: OAS recovery rate | B13: 0.15
A14: Capital gains inclusion rate | B14: 0.5 | C14: The proposed increase to a 2/3 inclusion rate was cancelled in March 2025; the rate remains 50%.
A15: Lifetime capital gains exemption | B15: 1250000
A16: Quebec abatement rate | B16: 0.165
A18: Trading note: for an active/scalp trader, profits are business income — the capital gains inclusion rate does not apply. See docs/trader_taxation.md.
